dashframe-0.3.0.dist-info/METADATA
dashframe-0.3.0.dist-info/WHEEL
dashframe-0.3.0.dist-info/entry_points.txt
dashframe-0.3.0.dist-info/licenses/LICENSE
dashframe/__init__.py
dashframe/components/compute.py
dashframe/components/footer.py
dashframe/components/header.py
dashframe/components/nav.py
dashframe/compress.py
dashframe/db.py
dashframe/examples.py
dashframe/log.py
dashframe/manager.py
dashframe/runner.py
dashframe-0.3.0.dist-info/RECORD
